stoqcompiler/__init__.py
stoqcompiler/compiler/__init__.py
stoqcompiler/compiler/compiler.py
stoqcompiler/compiler/compiler_action.py
stoqcompiler/compiler/compiler_result.py
stoqcompiler/hamiltonian/__init__.py
stoqcompiler/hamiltonian/hamiltonian.py
stoqcompiler/hamiltonian/hamiltonian_term.py
stoqcompiler/unitary/__init__.py
stoqcompiler/unitary/parameterized_unitary.py
stoqcompiler/unitary/parameterized_unitary_definitions.py
stoqcompiler/unitary/parameterized_unitary_parameter.py
stoqcompiler/unitary/unitary.py
stoqcompiler/unitary/unitary_definitions.py
stoqcompiler/unitary/unitary_primitive.py
stoqcompiler/unitary/unitary_sequence.py
stoqcompiler/unitary/unitary_sequence_entry.py
stoqcompiler/verification/__init__.py
stoqcompiler/verification/verification.py
stoqcompiler-0.2.0.dist-info/LICENSE
stoqcompiler-0.2.0.dist-info/METADATA
stoqcompiler-0.2.0.dist-info/WHEEL
stoqcompiler-0.2.0.dist-info/top_level.txt
stoqcompiler-0.2.0.dist-info/RECORD
