Metadata-Version: 2.1
Name: stoqcompiler
Version: 0.2.0
Summary: Toolset for stochastic approximate quantum compilation.
Home-page: https://github.com/rmshaffer/stoq-compiler
Author: Ryan Shaffer
Author-email: ryan@ryanshaffer.net
License: UNKNOWN
Platform: UNKNOWN
Classifier: Programming Language :: Python :: 3
Classifier: License :: OSI Approved :: MIT License
Classifier: Operating System :: OS Independent
Requires-Python: >=3.6
License-File: LICENSE
